{
  "doctors": [
    {
      "status": "yönetici-rüya",
      "age": 19,
      "id": 7
    },
    {
      "status": "Master",
      "age": 44,
      "id": 8
    }
  ],
  "comments": [],
  "users": [
    {
      "id": 1,
      "username": "ngumus",
      "password": "ngumus",
      "email": "ngumus@gumus.com"
    },
    {
      "username": "nazlignca",
      "email": "nazlignca@hotmail.com",
      "password": "Nazli.online21*",
      "repeatPassword": "Nazli.online21*",
      "id": 2
    },
    {
      "username": "nazlignca",
      "email": "nazlignca@hotmail.com",
      "password": "Nazli.online21*",
      "repeatPassword": "Nazli.online21*",
      "id": 3
    },
    {
      "username": "nazlignca",
      "email": "nazlignca@hotmail.com",
      "password": "Nazli.online21*",
      "repeatPassword": "Nazli.online21*",
      "id": 4
    },
    {
      "username": "nazlignca",
      "email": "nazlignca@hotmail.com",
      "password": "Nazli.online21*",
      "repeatPassword": "Nazli.online21*",
      "id": 5
    },
    {
      "username": "nazlignca",
      "email": "nazlignca@hotmail.com",
      "password": "Nazli.online21*",
      "repeatPassword": "Nazli.online21*",
      "id": 6
    }
  ],
  "login": [
    {
      "id": 1,
      "username": "ngumus",
      "password": "ngumus"
    }
  ],
  "nazlis": [],
  "profile": {
    "name": "typicode"
  },
  "posts": [
    {
      "title": "şmknjbhvghcfghvjbhkn",
      "author": "vsdvds",
      "id": 1
    }
  ]
}